gcf_utility_functions/__init__.py
gcf_utility_functions/gmail_helper.py
gcf_utility_functions/google_service_access.py
gcf_utility_functions-0.0.1.dist-info/METADATA
gcf_utility_functions-0.0.1.dist-info/RECORD
gcf_utility_functions-0.0.1.dist-info/WHEEL
gcf_utility_functions-0.0.1.dist-info/top_level.txt
